setup.cfg
setup.py
caenbrew/__init__.py
caenbrew/__main__.py
caenbrew/packaging.py
caenbrew.egg-info/PKG-INFO
caenbrew.egg-info/SOURCES.txt
caenbrew.egg-info/dependency_links.txt
caenbrew.egg-info/entry_points.txt
caenbrew.egg-info/requires.txt
caenbrew.egg-info/top_level.txt
caenbrew/packages/__init__.py
caenbrew/packages/caenbrew.py
caenbrew/packages/clang.py
caenbrew/packages/cmake.py
caenbrew/packages/cppcheck.py
caenbrew/packages/emacs.py
caenbrew/packages/fish.py
caenbrew/packages/git.py
caenbrew/packages/libevent.py
caenbrew/packages/ncurses.py
caenbrew/packages/pip.py
caenbrew/packages/python3.py
caenbrew/packages/tmux.py
caenbrew/packages/vim.py
test/test_packaging.py