Metadata-Version: 1.0
Name: caenbrew
Version: 1.0.0
Summary: Install packages on CAEN.
Home-page: https://github.com/arxanas/caenbrew
Author: Waleed Khan
Author-email: wkhan@umich.edu
License: UNKNOWN
Platform: UNKNOWN
